langchain_addons/__init__.py
langchain_addons/agents.py
langchain_addons-0.0.2.dist-info/LICENSE
langchain_addons-0.0.2.dist-info/METADATA
langchain_addons-0.0.2.dist-info/WHEEL
langchain_addons-0.0.2.dist-info/top_level.txt
langchain_addons-0.0.2.dist-info/RECORD
