Metadata-Version: 2.1
Name: langchain-addons
Version: 0.0.2
Summary: ...
Home-page: UNKNOWN
Author: Eduardo M. de Morais
Author-email: emdemor415@gmail.com
License: MIT License
Keywords: preprocessing
Platform: UNKNOWN
Requires-Dist: langchain
